{
    "features": [
        {
            "geometry": {
                "coordinates": [
                    -73.32612,
                    5.599811
                ],
                "type": "Point"
            },
            "properties": {
                "description": "Despacho CDA",
                "name": "Despacho CDA"
            },
            "type": "Feature"
        },
        {
            "geometry": {
                "coordinates": [
                    -73.374315,
                    5.512662
                ],
                "type": "Point"
            },
            "properties": {
                "description": "Punto de Retorno",
                "name": "Punto de Retorno"
            },
            "type": "Feature"
        }
    ],
    "type": "FeatureCollection"
}
